fastq/__init__.py
fastq/_fastq.py
fastq/_reader.py
fastq/_writer.py
fastq-2.0.4.dist-info/LICENSE
fastq-2.0.4.dist-info/METADATA
fastq-2.0.4.dist-info/WHEEL
fastq-2.0.4.dist-info/top_level.txt
fastq-2.0.4.dist-info/RECORD
