Metadata-Version: 2.1
Name: fastq
Version: 2.0.4
Summary: A simple FASTQ reader / toolbox for small to medium size projects without dependencies.
Home-page: https://github.com/not-a-feature/fastq
Author: Jules Kreuer / not_a_feature
License: gpl-3.0
Keywords: FASTQ,fastq,reader,toolbox,bio,bioinformatics
Platform: unix
Platform: linux
Platform: osx
Platform: cygwin
Platform: win32
Classifier: Programming Language :: Python :: 3
Requires-Python: >=3.8
License-File: LICENSE
Provides-Extra: testing
Requires-Dist: pytest >=7.1 ; extra == 'testing'
Requires-Dist: pytest-cov >=4.0 ; extra == 'testing'
Requires-Dist: tox >=3.24 ; extra == 'testing'
Requires-Dist: black >=21.1 ; extra == 'testing'
